simple-cpus/rv32-single/rv32-single.srcs/sources_1/new/defines.v
// OPCODE by type
`define op_r 7'b0110011
`define op_b 7'b1100011
`define op_s 7'b0100011
`define op_l 7'b0000011
`define op_i 7'b0010011

// RV32I opcodes
`define op_lui 7'b0110111
`define op_auipe 7'b0010111
`define op_jal 7'b1101111
`define op_jalr 7'b1100111
`define op_beq 7'b1100011
`define op_bne 7'b1100011
`define op_blt 7'b1100011
`define op_bge 7'b1100011
`define op_bltu 7'b1100011
`define op_bgeu 7'b1100011
`define op_lb 7'b0000011
`define op_lh 7'b0000011
`define op_lw 7'b0000011
`define op_lbu 7'b0000011
`define op_lhu 7'b0000011
`define op_sb 7'b0100011
`define op_sh 7'b0100011
`define op_sw 7'b0100011
`define op_addi 7'b0010011
`define op_slti 7'b0010011
`define op_sltiu 7'b0010011
`define op_xori 7'b0010011
`define op_ori 7'b0010011
`define op_andi 7'b0010011
`define op_slli 7'b0010011
`define op_srli 7'b0010011
`define op_srai 7'b0010011
`define op_add 7'b0110011
`define op_sub 7'b0110011
`define op_sll 7'b0110011
`define op_slt 7'b0110011
`define op_sltu 7'b0110011
`define op_xor 7'b0110011
`define op_srl 7'b0110011
`define op_sra 7'b0110011
`define op_or 7'b0110011
`define op_and 7'b0110011
`define op_fence 7'b0001111
`define op_fencei 7'b0001111
`define op_ecall 7'b1110011
`define op_ebreak 7'b1110011
`define op_csrrw 7'b1110011
`define op_csrrs 7'b1110011
`define op_csrrc 7'b1110011
`define op_csrrwi 7'b1110011
`define op_csrrsi 7'b1110011
`define op_csrrci 7'b1110011

// RV32I funct3 codes
`define f3_jalr 3'b000
`define f3_beq 3'b000
`define f3_bne 3'b001
`define f3_blt 3'b100
`define f3_bge 3'b101
`define f3_bltu 3'b110
`define f3_bgeu 3'b111
`define f3_lb 3'b000
`define f3_lh 3'b001
`define f3_lw 3'b010
`define f3_lbu 3'b100
`define f3_lhu 3'b101
`define f3_sb 3'b000
`define f3_sh 3'b001
`define f3_sw 3'b010
`define f3_addi 3'b000
`define f3_slti 3'b010
`define f3_sltiu 3'b011
`define f3_xori 3'b100
`define f3_ori 3'b110
`define f3_andi 3'b111
`define f3_slli 3'b001
`define f3_srli 3'b101
`define f3_srai 3'b101
`define f3_add 3'b000
`define f3_sub 3'b000
`define f3_sll 3'b001
`define f3_slt 3'b010
`define f3_sltu 3'b011
`define f3_xor 3'b100
`define f3_srl 3'b101
`define f3_sra 3'b101
`define f3_or 3'b110
`define f3_and 3'b111
`define f3_fence 3'b000
`define f3_fencei 3'b001
`define f3_ecall 3'b000
`define f3_ebreak 3'b000
`define f3_csrrw 3'b001
`define f3_csrrs 3'b010
`define f3_csrrc 3'b011
`define f3_csrrwi 3'b101
`define f3_csrrsi 3'b110
`define f3_csrrci 3'b111

// RV32I func7 codes
`define  f7_slli 7'b0000000
`define f7_srli 7'b0000000
`define f7_srai 7'b0100000
`define f7_add 7'b0000000
`define f7_sub 7'b0100000
`define f7_sll 7'b0000000
`define f7_slt 7'b0000000
`define f7_sltu 7'b0000000
`define f7_xor 7'b0000000
`define f7_srl 7'b0000000
`define f7_sra 7'b0100000
`define f7_or 7'b0000000
`define f7_and 7'b0000000

// RV32M opcodes
`define op_mul 7'b0110011
`define op_mulh 7'b0110011
`define op_mulhsu 7'b0110011
`define op_mulhu 7'b0110011
`define op_div 7'b0110011
`define op_divu 7'b0110011
`define op_rem 7'b0110011
`define op_remu 7'b0110011

// RV32M f7 codes
`define f7_mul 7'b0000001
`define f7_mulh 7'b0000001
`define f7_mulhsu 7'b0000001
`define f7_mulhu 7'b0000001
`define f7_div 7'b0000001
`define f7_divu 7'b0000001
`define f7_rem 7'b0000001
`define f7_remu 7'b0000001

// RV32M f3 codes
`define f3_mul 3'b000
`define f3_mulh 3'b001
`define f3_mulhsu 3'b010
`define f3_mulhu 3'b011
`define f3_div 3'b100
`define f3_divu 3'b101
`define f3_rem 3'b110
`define f3_remu 3'b111

// ALU Opcodes
// Control for alu opcode
`define ALU_ADD 4'b0001
`define ALU_ADDH 4'b0010
`define ALU_ADDB 4'b0011
`define ALU_ADDU 4'b0100
`define ALU_SUB 4'b0101
`define ALU_SLL 4'b0110
`define ALU_SLT 4'b0111
`define ALU_SLTU 4'b1000
`define ALU_XOR 4'b1001
`define ALU_SRL 4'b1010
`define ALU_SRA 4'b1011
`define ALU_OR 4'b1100
`define ALU_AND 4'b1101

simple-cpus/rv32-single/rv32-single.srcs/sources_1/new/alu.v
`include "defines.v"
`timescale 1ns / 1ps

// Page 351 of pdf (270 in actual textbook)

module alu (
	input r,
	input [3:0] alu_op,
	input [31:0] alu_in1,
	input [31:0] alu_in2,
	output wire zero,
	output reg [31:0] alu_result
);
	
	localparam ADD = 4'b0010;
	localparam SUB = 4'b0110;
	localparam AND = 4'b0000;
	localparam OR = 4'b0001;
	
	wire signed [31:0] alu_in1_signed = alu_in1;
	wire signed [31:0] alu_in2_signed = alu_in2;
	
	assign zero = (alu_in1_signed - alu_in2_signed == 0) ? 1'b1 : 1'b0;
	
	always @(*) begin
		if (r) begin
            alu_result = 0;	
		end
		else begin
		  case(alu_op)
			ADD : alu_result = alu_in1_signed + alu_in2_signed; // add
			SUB : alu_result = alu_in1_signed - alu_in2_signed; // sub					
			OR : alu_result = alu_in1_signed | alu_in2_signed; // or
			AND : alu_result = alu_in1_signed & alu_in2_signed; // and 			
			default : alu_result = 0;
		  endcase
		end
	end
	
endmodule

simple-cpus/rv32-multi/rv32-multi.srcs/sources_1/new/alu_control.v
`timescale 1ns / 1ps

// Page 352 of pdf (271 in actual textbook)

module alu_control(
    input wire r,
    input wire [1:0] alu_op,
    input wire [9:0] func_code, //{f7, f3}
    output reg [3:0] operation
);

    always @(*) begin
        if (r) begin
            operation = 4'b0000;
        end
        else begin
            casex({alu_op, func_code})
                {2'b00, 10'bxxxxxxxxxx} : operation = 4'b0010;
                {2'bx1, 10'bxxxxxxxxxx} : operation = 4'b0110;
                {2'b1x, 10'b0000000000} : operation = 4'b0010;
                {2'b1x, 10'b0100000000} : operation = 4'b0110;
                {2'b1x, 10'b0000000111} : operation = 4'b0000;
                {2'b1x, 10'b0000000110} : operation = 4'b0001;
                default : operation = 4'b0000;
            endcase
        end
    end


endmodule

simple-cpus/rv32-single/rv32-single.srcs/sources_1/new/immediate_generator.v
`timescale 1ns / 1ps
`include "defines.v"

module immediate_generator(
    input r,
    input [31:0] instruction,
    output reg [31:0] imm_sext
);

    always @(*) begin
        if (r) begin
            imm_sext = 0;
        end
        else begin
            case(instruction[6:0])
            `op_b : begin
                imm_sext = {{19{instruction[31]}}, instruction[31], instruction[7], instruction[30:25], instruction[11:8], 1'b0};
            end
            `op_i : begin
                imm_sext = {{20{instruction[31]}}, instruction[31:20]};
            end
            `op_s : begin
                imm_sext = {{20{instruction[31]}} ,instruction[31:25], instruction[11:7]};
            end
            `op_l : begin
                imm_sext = {{20{instruction[31]}}, instruction[31:20]};
            end
            `op_jal : begin
                imm_sext = {{12{instruction[31]}}, instruction[31], instruction[19:12], instruction[20], instruction[30:21]};
            end
            `op_jalr : begin
                imm_sext = {{20{instruction[31]}}, instruction[31:20]};
            end
            `op_lui : begin
                imm_sext = {{12{instruction[31]}}, instruction[31:12]};
            end
            `op_auipe : begin
                imm_sext = {{12{instruction[31]}}, instruction[31:12]};
            end
            default : begin
                imm_sext = 0;
            end
            endcase
        end
    end
    
endmodule

rv32-single/rv32-single.srcs/sources_1/new/register_file.v
`timescale 1ns / 1ps
module register_file (
    input wire r,
    input wire [4:0] rs1, 
    input wire [4:0] rs2, 
    input wire [4:0] write_addr,
    input wire write_enable,
    input wire [31:0] write_data,
    output reg [31:0] read_data1,
    output reg [31:0] read_data2
);

    localparam REGSIZE = 32;
    localparam NUMREGS = 32;
    reg [REGSIZE-1:0] regs[0:NUMREGS - 1];
    
    integer i;
    initial begin
       for (i = 0; i < NUMREGS; i = i + 1) begin
           if (i == 1) begin
               regs[i] = 1;
           end
           
           else if (i == 2) begin
               regs[i] = 5;
           end
           
           else begin
               regs[i] = 0;
           end
       end
    end
    
    always @(*) begin
        if (r) begin
            read_data1 = 0;
            read_data2 = 0;
        end
        else begin
            if (write_enable) begin
                regs[write_addr] = write_data;
                read_data1 = (rs1 == 0) ? 32'd0 : regs[rs1];
                read_data2 = (rs2 == 0) ? 32'd0 : regs[rs2];
            end
            else begin
                read_data1 = (rs1 == 0) ? 32'd0 : regs[rs1];
                read_data2 = (rs2 == 0) ? 32'd0 : regs[rs2];
            end
        end
    end
  
endmodule

rv32-multi/rv32-multi.srcs/sources_1/new/control_unit.v
`timescale 1ns / 1ps
`include "defines.v"

// FSM on page 381 of HP1 

module control_unit(
    input clk,
    input r,
    input [6:0] op_code,
	output reg pc_write_cond,
	output reg [1:0] pc_source,
	output reg pc_write,
	output reg [1:0] alu_op,
	output reg i_or_d,
	output reg [1:0] alu_srcB,
	output reg mem_read,
	output reg alu_srcA,
	output reg mem_write,
	output reg mem_2_reg,
	output reg reg_write,
	output reg ir_write
);

    reg [4:0] state;
    localparam INSTR_FETCH = 0;
    localparam INSTR_DEC = 1;
    localparam MEM_ADDR_COMP = 2;
    localparam MEM_ACCESS1 = 3;
    localparam MEM_READ_COMP = 4;
    localparam MEM_ACCESS2 = 5;
    localparam EXEC = 6;
    localparam R_COMPLETE = 7;
    localparam B_COMPLETE = 8;
    
    always @(posedge clk) begin
        if (r) begin
            state <= INSTR_FETCH;
            mem_read <= 1;
            mem_write <= 0;
            mem_2_reg <= 0;
            reg_write <= 0;
            alu_srcA <= 0;
            i_or_d <= 0;
            ir_write <= 1;
            alu_srcB <= 2'b01;
            alu_op <= 2'b00;
            pc_write <= 1;
            pc_source <= 0;
            pc_write_cond <= 0;
        end
        else begin
            case(state)
                INSTR_FETCH : begin
                    state <= INSTR_DEC;
                    alu_srcA <= 0;
                    alu_srcB <= 2'b10;
                    alu_op <= 2'b00;
                    mem_read <= 0;
                    pc_write <= 0;
                    ir_write <= 0;
                end
                INSTR_DEC : begin
                    state <= ((op_code == `op_l || op_code == `op_s) && !r) ? MEM_ADDR_COMP :
                             (op_code == `op_r && !r) ? EXEC :
                             (op_code == `op_b && !r) ? B_COMPLETE : 0;
                    
                    alu_srcA <= (!r) ? 1 : 0;
                    
                    alu_srcB <= ((op_code == `op_l || op_code == `op_s) && !r) ? 2'b10 :
                             ((op_code == `op_r || op_code == `op_b) && !r) ? 2'b00 : 0;
                    
                    alu_op <= ((op_code == `op_l || op_code == `op_s) && !r) ? 2'b00 :
                             (op_code == `op_r && !r) ? 2'b10 :
                             (op_code == `op_b && !r) ? 2'b01 : 0;
                             
                    pc_write_cond <= (op_code == `op_b && !r) ? 1 : 0;
                    pc_source <= (op_code == `op_b && !r) ? 1 : 0;
                end
                MEM_ADDR_COMP : begin
                    state <= (op_code == `op_l && !r) ? MEM_ACCESS1 :
                             (op_code == `op_s && !r) ? MEM_ACCESS2 : 0;
                             
                    mem_read <= (op_code == `op_l && !r) ? 1 : 0;
                    mem_write <= (op_code == `op_s && !r) ? 1 : 0;
                    i_or_d <= 1;
                     
                end
                MEM_ACCESS1 : begin
                    state <= MEM_READ_COMP;
                    reg_write <= 1;
                    mem_2_reg <= 1;
                end
                MEM_READ_COMP : begin
                    state <= INSTR_FETCH;
                    mem_read <= 1;
                    mem_write <= 0;
                    mem_2_reg <= 0;
                    reg_write <= 0;
                    alu_srcA <= 0;
                    i_or_d <= 0;
                    ir_write <= 1;
                    alu_srcB <= 2'b01;
                    alu_op <= 2'b00;
                    pc_write <= 1;
                    pc_source <= 0;
                    pc_write_cond <= 0;
                end
                MEM_ACCESS2 : begin
                    state <= INSTR_FETCH;
                    mem_read <= 1;
                    mem_write <= 0;
                    mem_2_reg <= 0;
                    reg_write <= 0;
                    alu_srcA <= 0;
                    i_or_d <= 0;
                    ir_write <= 1;
                    alu_srcB <= 2'b01;
                    alu_op <= 2'b00;
                    pc_write <= 1;
                    pc_source <= 0;
                    pc_write_cond <= 0;
                end
                EXEC : begin
                    state <= R_COMPLETE;
                    reg_write <= 1;
                    mem_2_reg <= 0;
                end
                R_COMPLETE : begin
                    state <= INSTR_FETCH;
                    mem_read <= 1;
                    mem_write <= 0;
                    mem_2_reg <= 0;
                    reg_write <= 0;
                    alu_srcA <= 0;
                    i_or_d <= 0;
                    ir_write <= 1;
                    alu_srcB <= 2'b01;
                    alu_op <= 2'b00;
                    pc_write <= 1;
                    pc_source <= 0;
                    pc_write_cond <= 0;
                end
                B_COMPLETE : begin
                    state <= INSTR_FETCH;
                    mem_read <= 1;
                    mem_write <= 0;
                    mem_2_reg <= 0;
                    reg_write <= 0;
                    alu_srcA <= 0;
                    i_or_d <= 0;
                    ir_write <= 1;
                    alu_srcB <= 2'b01;
                    alu_op <= 2'b00;
                    pc_write <= 1;
                    pc_source <= 0;
                    pc_write_cond <= 0;
                end
                default : begin
                    state <= INSTR_FETCH;
                    mem_read <= 1;
                    mem_write <= 0;
                    mem_2_reg <= 0;
                    reg_write <= 0;
                    alu_srcA <= 0;
                    i_or_d <= 0;
                    ir_write <= 1;
                    alu_srcB <= 2'b01;
                    alu_op <= 2'b00;
                    pc_write <= 1;
                    pc_source <= 0;
                    pc_write_cond <= 0;
                end
            endcase
        end    
    end

    

endmodule

simple-cpus/rv32-multi/rv32-multi.srcs/sources_1/new/memory.v
`timescale 1ns / 1ps

module memory(
    input wire r,
    input wire [31:0] address,
    input wire [31:0] write_data,
    input wire mem_read,
    input wire mem_write,
    output reg [31:0] mem_data
);
    
    localparam MEM_SIZE = 2048;
    reg [31:0] memory [0:MEM_SIZE - 1];
    
    always @(*) begin
        if (r) begin
            mem_data = 0;        
        end
        else begin
            if (mem_read) begin
                mem_data <= memory[address]; 
            end
            else if (mem_write) begin
                memory[address] <= write_data;
            end
        end
    end
    
    integer i;
    initial begin
        // Initialize memory with zeros or predefined values
        for (i = 0; i < MEM_SIZE; i = i + 1) begin
            if (i == 0) begin
                memory[i] = 32'b0000000_00010_00001_000_00011_0110011; // add x3, x1, x2
            end
            else if (i == 1) begin
                memory[i] = 32'b0100000_00001_00010_000_00100_0110011; // sub x4, x2, x1
            end
            else if (i == 2) begin
                memory[i] = 32'b0000000_00010_00001_111_00101_0110011; // and x5, x1, x2
            end
            else if (i == 3) begin
                memory[i] = 32'b0000000_00010_00100_110_00110_0110011; // or x6, x4, x2
            end
            else if (i == 4) begin
                memory[i] = 32'b000001000000_00000_010_00111_0000011; // lw x7, 64(x0)
            end
            else if (i == 5) begin
                memory[i] = 32'b0000000_01000_00000_010_00001_0100011; // sw x8, 1(x0)
            end
            else if (i == 6) begin
                memory[i] = 32'b0000000_00110_00010_000_01010_1100011; // beq x2, x6, offset
            end
            else if (i == 7) begin
                memory[i] = 32'b0; // jalr
            end
            else if (i == 64) begin
                memory[i] = 68;
            end
            else begin
                memory[i] = 32'b0;
            end
        end
    end
    
endmodule

simple-cpus/rv32-multi/rv32-multi.srcs/sources_1/new/riscv_cpu.v
`timescale 1ns / 1ps
// Block diagram on page 368 of pdf of HP 1
module riscv_cpu(
    input clk,
    input r,
    input [31:0] i_mem_addr,
	input [31:0] i_mem_data,
	input i_mem_write
);

reg [31:0] PC, alu_out;
wire zero, pc_write, pc_write_cond;
wire [1:0] pc_source;
wire [31:0] alu_result, target, imm_sext;
assign target = (pc_source == 2'b10) ? imm_sext : 
                (pc_source == 2'b01) ? alu_out : alu_result;
always @(posedge clk) begin
    if (r) begin
        PC <= 0;
    end
    else begin
        if ((pc_write_cond && zero) || pc_write) begin
            PC <= target;
        end
        else begin
            PC <= PC;
        end
    end
end

reg [31:0] B;
wire [31:0] mem_data;
wire [31:0] address;
wire i_or_d, mem_read, mem_write;
assign address = (i_or_d) ? alu_out : PC;
memory m1(
    .r(r),
    .address(address),
    .write_data(B),
    .mem_read(mem_read),
    .mem_write(mem_write),
    .mem_data(mem_data)
);

reg [31:0] instr_o;
wire ir_write;
always @(posedge clk) begin
    if (r) begin
        instr_o <= 0;
    end
    else begin
        if (ir_write) begin
            instr_o <= mem_data;
        end
    end
end

reg [31:0] mem_data_o;
always @(posedge clk) begin
    if (r) begin
        mem_data_o <= 0;
    end
    else begin
        mem_data_o <= mem_data;
    end
end

wire alu_srcA, mem_2_reg, reg_write;
wire [1:0] alu_srcB, alu_op;
control_unit cu1(
    .clk(clk),
    .r(r),
    .op_code(instr_o),
	.pc_write_cond(pc_write_cond),
	.pc_source(pc_source),
	.pc_write(pc_write),
	.alu_op(alu_op),
	.i_or_d(i_or_d),
	.alu_srcB(alu_srcB),
	.mem_read(mem_read),
	.alu_srcA(alu_srcA),
	.mem_write(mem_write),
	.mem_2_reg(mem_2_reg),
	.reg_write(reg_write),
	.ir_write(ir_write)
);

wire [31:0] read_data1, read_data2, write_data;
assign write_data = (mem_2_reg) ? mem_data_o : alu_out;
register_file rf1(
    .r(r),
    .rs1(instr_o[19:15]), 
    .rs2(instr_o[24:20]), 
    .write_addr(instr_o[11:7]),
    .write_enable(reg_write),
    .write_data(write_data),
    .read_data1(read_data1),
    .read_data2(read_data2)
);

immediate_generator ig1(
    .r(r),
    .instruction(instr_o),
    .imm_sext(imm_sext)
);

wire [3:0] operation;
alu_control ac1(
    .r(r),
    .alu_op(alu_op),
    .func_code({instr_o[31:25], instr_o[14:12]}), //{f7, f3}
    .operation(operation)
);

reg [31:0] A;
always @(posedge clk) begin
    if (r) begin
        A <= 0;
    end
    else begin
        A <= read_data1;
    end
end

always @(posedge clk) begin
    if (r) begin
        B <= 0;
    end
    else begin
        B <= read_data2;
    end
end

wire [31:0] alu_in1, alu_in2;
assign alu_in1 = (alu_srcA) ? A : PC;
assign alu_in2 = (alu_srcB == 2'b01) ? 1 : (alu_srcB == 2'b10) ? imm_sext : B;
alu alu1(
    .r(r),
	.alu_op(operation),
	.alu_in1(alu_in1),
	.alu_in2(alu_in2),
	.zero(zero),
	.alu_result(alu_result)
);

always @(posedge clk) begin
    if (r) begin
        alu_out <= 0;        
    end
    else begin
        alu_out <= alu_result;
    end
end


endmodule

rv32-single/rv32-single.srcs/sources_1/new/riscv_cpu_tb.v
`timescale 1ns / 1ps
module riscv_cpu_tb();

    reg clk = 1;
    reg r;
    reg [31:0] i_mem_addr;
	reg [31:0] i_mem_data;
	reg i_mem_write;
    
    riscv_cpu dut(
        .clk(clk),
        .r(r),
        .i_mem_addr(i_mem_addr),
        .i_mem_data(i_mem_data),
        .i_mem_write(i_mem_write)
    );
    
    always begin
        # 5 clk = ~clk;    
    end
    
    initial begin
        $monitor("At time %t", $time);
      	$dumpfile("riscv_cpu_tb.vcd");
      	$dumpvars(0, riscv_cpu_tb);
      	r = 1;
      	i_mem_addr = 0;
      	i_mem_data = 0;
      	i_mem_write = 0;
      	# 5
      	r = 0;
      	# 20
      	$finish;
    end
    
endmodule

simple-cpus/rv32-multi/rv32-multi.sim/sim_1/behav/xsim/riscv_cpu_tb.vcd
$date
   Tue Dec  5 15:16:13 2023
$end
$version
  2023.1
$end
$timescale
  1ps
$end
$scope module riscv_cpu_tb $end
$var reg 1 ! clk $end
$var reg 1 " r $end
$var reg 32 # i_mem_addr [31:0] $end
$var reg 32 $ i_mem_data [31:0] $end
$var reg 1 % i_mem_write $end
$scope module dut $end
$var wire 1 & clk $end
$var wire 1 ' r $end
$var wire 32 ( i_mem_addr [31:0] $end
$var wire 32 ) i_mem_data [31:0] $end
$var wire 1 * i_mem_write $end
$var reg 32 + PC [31:0] $end
$var reg 32 , alu_out [31:0] $end
$var wire 1 - zero $end
$var wire 1 . pc_write $end
$var wire 1 / pc_write_cond $end
$var wire 2 0 pc_source [1:0] $end
$var wire 32 1 alu_result [31:0] $end
$var wire 32 2 target [31:0] $end
$var wire 32 3 imm_sext [31:0] $end
$var reg 32 4 B [31:0] $end
$var wire 32 5 mem_data [31:0] $end
$var wire 32 6 address [31:0] $end
$var wire 1 7 i_or_d $end
$var wire 1 8 mem_read $end
$var wire 1 9 mem_write $end
$var reg 32 : instr_o [31:0] $end
$var wire 1 ; ir_write $end
$var reg 32 < mem_data_o [31:0] $end
$var wire 1 = alu_srcA $end
$var wire 1 > mem_2_reg $end
$var wire 1 ? reg_write $end
$var wire 2 @ alu_srcB [1:0] $end
$var wire 2 A alu_op [1:0] $end
$var wire 32 B read_data1 [31:0] $end
$var wire 32 C read_data2 [31:0] $end
$var wire 32 D write_data [31:0] $end
$var wire 4 E operation [3:0] $end
$var reg 32 F A [31:0] $end
$var wire 32 G alu_in1 [31:0] $end
$var wire 32 H alu_in2 [31:0] $end
$scope module m1 $end
$var wire 1 ' r $end
$var wire 32 6 address [31:0] $end
$var wire 32 I write_data [31:0] $end
$var wire 1 8 mem_read $end
$var wire 1 9 mem_write $end
$var reg 32 J mem_data [31:0] $end
$var integer 32 K i [31:0] $end
$upscope $end
$scope module cu1 $end
$var wire 1 & clk $end
$var wire 1 ' r $end
$var wire 7 L op_code [6:0] $end
$var reg 1 M pc_write_cond $end
$var reg 2 N pc_source [1:0] $end
$var reg 1 O pc_write $end
$var reg 2 P alu_op [1:0] $end
$var reg 1 Q i_or_d $end
$var reg 2 R alu_srcB [1:0] $end
$var reg 1 S mem_read $end
$var reg 1 T alu_srcA $end
$var reg 1 U mem_write $end
$var reg 1 V mem_2_reg $end
$var reg 1 W reg_write $end
$var reg 1 X ir_write $end
$var reg 5 Y state [4:0] $end
$upscope $end
$scope module rf1 $end
$var wire 1 ' r $end
$var wire 5 Z rs1 [4:0] $end
$var wire 5 [ rs2 [4:0] $end
$var wire 5 \ write_addr [4:0] $end
$var wire 1 ? write_enable $end
$var wire 32 D write_data [31:0] $end
$var reg 32 ] read_data1 [31:0] $end
$var reg 32 ^ read_data2 [31:0] $end
$var integer 32 _ i [31:0] $end
$upscope $end
$scope module ig1 $end
$var wire 1 ' r $end
$var wire 32 ` instruction [31:0] $end
$var reg 32 a imm_sext [31:0] $end
$upscope $end
$scope module ac1 $end
$var wire 1 ' r $end
$var wire 2 A alu_op [1:0] $end
$var wire 10 b func_code [9:0] $end
$var reg 4 c operation [3:0] $end
$upscope $end
$scope module alu1 $end
$var wire 1 ' r $end
$var wire 4 E alu_op [3:0] $end
$var wire 32 G alu_in1 [31:0] $end
$var wire 32 H alu_in2 [31:0] $end
$var wire 1 - zero $end
$var reg 32 d alu_result [31:0] $end
$var wire 32 e alu_in1_signed [31:0] $end
$var wire 32 f alu_in2_signed [31:0] $end
$upscope $end
$upscope $end
$upscope $end
$enddefinitions $end
#0
$dumpvars
1!
1"
b0 #
b0 $
0%
1&
1'
b0 (
b0 )
0*
b0 +
b0 ,
0-
1.
0/
b0 0
b0 1
b0 2
b0 3
b0 4
b0 5
b0 6
07
18
09
b0 :
1;
b0 <
0=
0>
0?
b1 @
b0 A
b0 B
b0 C
b0 D
b0 E
b0 F
b0 G
b1 H
b0 I
b0 J
b100000000000 K
b0 L
0M
b0 N
1O
b0 P
0Q
b1 R
1S
0T
0U
0V
0W
1X
b0 Y
b0 Z
b0 [
b0 \
b0 ]
b0 ^
b100000 _
b0 `
b0 a
b0 b
b0 c
b0 d
b0 e
b1 f
$end
#5000
0!
0"
0&
0'
b1 1
b1 2
b1000001000000110110011 5
b10 E
b1000001000000110110011 J
b10 c
b1 d
#10000
1!
1&
b1 +
b1 ,
0-
0.
b1 1
b1 2
b1000000000100010000001000110011 5
b1 6
08
b1000001000000110110011 :
0;
b1000001000000110110011 <
b10 @
b1 B
b101 C
b1 D
b1 G
b0 H
b1000000000100010000001000110011 J
b110011 L
0O
b10 R
0S
0X
b1 Y
b1 Z
b10 [
b11 \
b1 ]
b101 ^
b1000001000000110110011 `
b1 d
b1 e
b0 f
#15000
0!
0&
#20000
1!
1&
b110 1
b110 2
b101 4
b1000000000100010000001000110011 <
1=
b0 @
b10 A
b1 F
b101 H
b101 I
b10 P
b0 R
1T
b110 Y
b110 d
b101 f
#25000
0!
0&
#30000
1!
1&
b110 ,
1?
b110 D
1W
b111 Y
#35000
0!
0&
#40000
1!
1&
1-
1.
b10 1
b10 2
18
1;
0=
0?
b1 @
b0 A
b1 H
1O
b0 P
b1 R
1S
0T
0W
1X
b0 Y
b10 d
b1 f
#45000
0!
0&
#50000
1!
1&
b10 +
b10 ,
0-
0.
b10 1
b10 2
b1000001111001010110011 5
b10 6
08
b1000000000100010000001000110011 :
0;
b10 @
b101 B
b1 C
b10 D
b10 G
b0 H
b1000001111001010110011 J
0O
b10 R
0S
0X
b1 Y
b10 Z
b1 [
b100 \
b101 ]
b1 ^
b1000000000100010000001000110011 `
b100000000 b
b10 d
b10 e
b0 f
#55000
0!
0&
#60000
1!
1&
b100 1
b100 2
b1 4
b1000001111001010110011 <
1=
b0 @
b10 A
b110 E
b101 F
b101 G
b1 H
b1 I
b10 P
b0 R
1T
b110 Y
b110 c
b100 d
b101 e
b1 f
#65000
0!
0&
#70000
1!
1&
b100 ,
1?
b100 D
1W
b111 Y
#75000
0!
0&
#80000
1!
1&
1.
b11 1
b11 2
18
1;
0=
0?
b1 @
b0 A
b10 E
b10 G
1O
b0 P
b1 R
1S
0T
0W
1X
b0 Y
b10 c
b11 d
b10 e
#85000
0!
0&
#90000
1!
1&
b11 +
b11 ,
0.
b11 1
b11 2
b1000100110001100110011 5
b11 6
08
b1000001111001010110011 :
0;
b10 @
b1 B
b101 C
b11 D
b11 G
b0 H
b1000100110001100110011 J
0O
b10 R
0S
0X
b1 Y
b1 Z
b10 [
b101 \
b1 ]
b101 ^
b1000001111001010110011 `
b111 b
b11 d
b11 e
b0 f
#95000
0!
0&
#100000
1!
1&
b1 1
b1 2
b101 4
b1000100110001100110011 <
1=
b0 @
b10 A
b0 E
b1 F
b1 G
b101 H
b101 I
b10 P
b0 R
1T
b110 Y
b0 c
b1 d
b1 e
b101 f
#105000
0!
0&
#110000
1!
1&
b1 ,
1?
b1 D
1W
b111 Y
#115000
0!
0&
#120000
1!
1&
1.
b100 1
b100 2
18
1;
0=
0?
b1 @
b0 A
b10 E
b11 G
b1 H
1O
b0 P
b1 R
1S
0T
0W
1X
b0 Y
b10 c
b100 d
b11 e
b1 f
#125000
0!
0&
#130000
1!
1&
b100 +
b100 ,
0.
b100 1
b100 2
b100000000000010001110000011 5
b100 6
08
b1000100110001100110011 :
0;
b10 @
b100 B
b100 D
b100 G
b0 H
b100000000000010001110000011 J
0O
b10 R
0S
0X
b1 Y
b100 Z
b110 \
b100 ]
b1000100110001100110011 `
b110 b
b100 d
b100 e
b0 f
#135000
0!
0&
#140000
1!
1&
b101 1
b101 2
b100000000000010001110000011 <
1=
b0 @
b10 A
b1 E
b100 F
b101 H
b10 P
b0 R
1T
b110 Y
b1 c
b101 d
b101 f
#145000
0!
0&
#150000
1!
1&
b101 ,
1?
b101 D
1W
b111 Y
#155000
0!
0&
#160000
1!
1&
1.
18
1;
0=
0?
b1 @
b0 A
b10 E
b1 H
1O
b0 P
b1 R
1S
0T
0W
1X
b0 Y
b10 c
b1 f
#165000
0!
0&
#170000
1!
1&
b101 +
0.
b1000101 1
b1000101 2
b1000000 3
b100000000010000010100011 5
b101 6
08
b100000000000010001110000011 :
0;
b10 @
b0 B
b0 C
b101 G
b1000000 H
b100000000010000010100011 J
b11 L
0O
b10 R
0S
0X
b1 Y
b0 Z
b0 [
b111 \
b0 ]
b0 ^
b100000000000010001110000011 `
b1000000 a
b10010 b
b1000101 d
b101 e
b1000000 f
#175000
0!
0&
#180000
1!
1&
b1000101 ,
b1000000 1
b1000000 2
b0 4
b100000000010000010100011 <
1=
b1000101 D
b0 F
b0 G
b0 I
1T
b10 Y
b1000000 d
b0 e
#185000
0!
0&
#190000
1!
1&
b1000000 ,
b1000100 5
b1000000 6
17
18
b1000000 D
b1000100 J
1Q
1S
b11 Y
#195000
0!
0&
#200000
1!
1&
b1000100 <
1>
1?
b1000100 D
1V
1W
b100 Y
#205000
0!
0&
#210000
1!
1&
1.
b110 1
b110 2
b100000000010000010100011 5
b101 6
07
1;
0=
0>
0?
b1 @
b1000000 D
b101 G
b1 H
b100000000010000010100011 J
1O
0Q
b1 R
0T
0V
0W
1X
b0 Y
b110 d
b101 e
b1 f
#215000
0!
0&
#220000
1!
1&
b110 +
b110 ,
0.
b111 1
b111 2
b1 3
b11000010000010101100011 5
b110 6
08
b100000000010000010100011 :
0;
b100000000010000010100011 <
b10 @
b110 D
b110 G
b11000010000010101100011 J
b100011 L
0O
b10 R
0S
0X
b1 Y
b1000 [
b1 \
b100000000010000010100011 `
b1 a
b10 b
b111 d
b110 e
#225000
0!
0&
#230000
1!
1&
b111 ,
b1 1
b1 2
b11000010000010101100011 <
1=
b111 D
b0 G
1T
b10 Y
b1 d
b0 e
#235000
0!
0&
#240000
1!
1&
b1 ,
b1 6
17
19
b1 D
1Q
1U
b101 Y
#245000
0!
0&
#250000
1!
1&
1.
b111 1
b111 2
b110 6
07
18
09
1;
0=
b1 @
b110 G
1O
0Q
b1 R
1S
0T
0U
1X
b0 Y
b111 d
b110 e
#255000
0!
0&
#260000
1!
1&
b111 +
b111 ,
0.
b10001 1
b10001 2
b1010 3
b0 5
b111 6
08
b11000010000010101100011 :
0;
b10 @
b101 B
b101 C
b111 D
b111 G
b1010 H
b0 J
b1100011 L
0O
b10 R
0S
0X
b1 Y
b10 Z
b110 [
b1010 \
b101 ]
b101 ^
b11000010000010101100011 `
b1010 a
b0 b
b10001 d
b111 e
b1010 f
#265000
0!
0&
#270000
1!
1&
b10001 ,
1-
1/
b1 0
b0 1
b101 4
b0 <
1=
b0 @
b1 A
b10001 D
b110 E
b101 F
b101 G
b101 H
b101 I
1M
b1 N
b1 P
b0 R
1T
b1000 Y
b110 c
b0 d
b101 e
b101 f
#275000
0!
0&
