digital-building-blocks/combinational.v
`timescale 1ns / 1ps
//////////////////////////////////////////////////////////////////////////////////
// Company: 
// Engineer: 
// 
// Create Date: 09/30/2021 08:30:32 PM
// Design Name: 
// Module Name: sequential
// Project Name: 
// Target Devices: 
// Tool Versions: 
// Description: 
// 
// Dependencies: 
// 
// Revision:
// Revision 0.01 - File Created
// Additional Comments:
// 
//////////////////////////////////////////////////////////////////////////////////

/*
module combinational(

    );
endmodule
*/

module  Dec(a, b) ;
    parameter n = 2 ;
    parameter m = 4 ;
    
    input [n-1:0] a ;
    output [m-1:0] b ; 
    
    wire [m-1:0] b = 1<<a ;
endmodule

module Mux3(a2, a1, a0, s, b) ;
    parameter k = 1 ;
    input[k-1:0] a0, a1, a2 ; // inputs
    input[2:0] s ; // one hot select
    output[k-1:0] b;
    
    wire [k-1:0] b =  ({k{s[0]}} & a0) |
                      ({k{s[1]}} & a1) |
                      ({k{s[2]}} & a2) ; 
endmodule

module Muxb3(a2, a1, a0, sb, b) ;
    parameter k = 1 ;
    input[k-1:0] a0, a1, a2 ; // inputs
    input[1:0] sb ; // binary select
    output[k-1:0] b;
    wire [3:0] s ;
    
    Dec #(2, 3) d(sb, s) ;
    Mux3 #(k) m(a2, a1, a0, s, b) ;
endmodule

module Mux6a(a5, a4, a3, a2, a1, a0, s, b) ;
    parameter k = 1 ;
    input [k-1:0] a0, a1, a2, a3, a4, a5  ; // inputs
    input [5:0] s ; // one hot select
    output [k-1:0] b;
    wire [k-1:0] ba, bb ;
    wire [k-1:0] b = ba | bb ;
    
    Mux3 #(k) ma(a2, a1, a0, s[2:0], ba) ;
    Mux3 #(k) mb(a5, a4, a3, s[5:3], bb) ;
endmodule

module Enc42(a, b) ;
    input [3:0] a ;    
    output [1:0] b ;
    wire [1:0] b = {a[3] | a[2], a[3] | a[1]} ;
endmodule

module Enc42a(a, b, c) ;
    input [3:0] a ;
    output [1:0] b ;
    output c ;
    wire [1:0] b = {a[3] | a[2], a[3] | a[1]} ;
    wire c = |a ;
endmodule

module Enc164(a, b) ;
    input [15:0] a ;
    output [3:0] b ;
    wire [3:0] b ;
    wire [7:0] c ; 
    wire [3:0] d ; 
    
    Enc42a e0(a[3:0], c[1:0], d[0]) ;
    Enc42a e1(a[7:4], c[3:2], d[1]) ;
    Enc42a e2(a[11:8], c[5:4], d[2]) ;
    Enc42a e3(a[15:12], c[7:6], d[3]) ;
    
    Enc42 e4(d[3:0], b[3:2]) ;
    
    assign b[1] = c[1] | c[3] | c[5] | c[7] ;
    assign b[0] = c[0] | c[2] | c[4] | c[6] ;
    
endmodule

module Arb(r, g) ; 
    parameter n = 8 ;
    input [n-1:0] r ;
    output [n-1:0] g ;
    wire [n-1:0] c = {(~r[n-2:0] & c[n-2:0]), 1'b1} ;
    wire [n-1:0] g = r & c ; 
endmodule

module RArb(r, g) ;
    parameter n = 8 ;
    input [n-1:0] r ;
    output [n-1:0] g ;
    wire [n-1:0] c = {1'b1, (~r[n-1:1] & c[n-1:1])} ;
    wire [n-1:0] g = r & c ;
endmodule 

/*
module PriorityEncoder83(r, b) ; 
    input [7:0] r ;
    output [2:0] b ;
    wire [7:0] g ;
    Arb #(8) a(r, g) ; 
    Enc83 e(g, b) ;
endmodule
*/

module EqComp(a, b, eq) ;
    parameter k = 8 ;
    input [k-1:0] a, b ;
    output eq ;
    wire eq = (a == b) ;
endmodule

module MagComp(a, b, gt) ;
    parameter k = 8 ;
    input [k-1:0] a, b; 
    output gt ;
    wire [k-1:0] eqi = a ~^ b ;
    wire [k-1:0] gti = a & ~b ; 
    wire [k:0] gtb = {((eqi[k-1:0] & gtb[k-1:0]) | gti[k-1:0]), 1'b0} ;
    wire gt = gtb[k] ;
endmodule

digital-building-blocks/combinational_tb.v
module combinational_tb;

/*
parameter n = 2;
parameter m = 4;
reg [n-1:0] a;
wire [m-1:0] b;

Dec #(n,m) d1(a,b);



parameter k = 4;
reg [k-1 : 0] a0, a1, a2;
reg [2:0] s;
wire [3:0] b;

Mux3 #(k) mux(a2, a1, a0, s, b);


parameter k = 4;
reg [k-1 : 0] a0, a1, a2;
reg [1:0] sb;
wire [k-1:0] b;

Muxb3 #(k) muxb(a2, a1, a0, sb, b);


parameter k = 4;
reg [k-1 : 0] a0, a1, a2, a3, a4, a5;
reg [5:0] s;
wire [k-1:0] b;

Mux6a #(k) mux6(a0, a1, a2, a3, a4, a5, s, b);


   reg[3:0] a;
   wire [1:0] b;

   Enc42 enc42(a, b);


   reg[3:0] a;
   wire [1:0] b;
   wire	      c;
   Enc42a enc42a(a, b, c);


   reg[15:0] a;
   wire [3:0] b;

   Enc164 enc164(a, b);

   reg[7:0] r;
   wire [7:0] g;

   Arb arb(r, g);

   reg[7:0] r;
   wire [7:0] g;

   RArb rarb(r, g);

   reg[7:0] r;
   wire [2:0] b;

   PriorityEncoder83 pe83(r, b);

   reg[7:0] a, b;
   wire	    eq;

   EqComp ec(a, b, eq);
*/
   reg[7:0] a, b;
   wire	    gt;

   MagComp mc(a, b, gt);
   
// Test each possible input of a for decoder
/*
initial begin
    $monitor("At time %t, a = %d, b = %d", $time, a, b);
    $dumpfile("combinational_tb.vcd");
    $dumpvars(0, combinational_tb);
    # 5 a = 0;
    # 5 a = 1;
    # 5 a = 2;
    # 5 a = 3;
end

// Test for mux3
initial begin
    $monitor("At time %t, a0 = %d, a1 = %d, a2 = %d, sb = %d, b = %d", $time, a0, a1, a2, sb, b);
    $dumpfile("combinational_tb.vcd");
    $dumpvars(0, combinational_tb);
    
    # 5
    a0 = 0;
    a1 = 0;
    a2 = 0;
    s = 0;
    
    # 5
    a0 = 1;
    a1 = 2;
    a2 = 4;
    s = 0;
    
    # 5
    s = 1;
    
    #5
    s = 2;
    
    #5
    s = 4;
    
    #5
    $finish;
    
end

// muxb3 test 
initial begin
    $monitor("At time %t, a0 = %d, a1 = %d, a2 = %d, sb = %d, b = %d", $time, a0, a1, a2, sb, b);
    $dumpfile("combinational_tb.vcd");
    $dumpvars(0, combinational_tb);
    
    # 5
    a0 = 0;
    a1 = 0;
    a2 = 0;
    sb = 0;
    
    # 5
    a0 = 1;
    a1 = 2;
    a2 = 4;
    sb = 0;
    
    # 5
    sb = 1;
    
    #5
    sb = 2;
    
    #5
    sb = 4;
    
    #5
    $finish;
    
end



// mux6 test
initial begin
    $monitor("At time %t, a0 = %d, a1 = %d, a2 = %d, a3 = %d, a4 = %d, a5 = %d, s = %d, b = %d", $time, a0, a1, a2, a3, a4, a5, s, b);
    $dumpfile("combinational_tb.vcd");
    $dumpvars(0, combinational_tb);
    
    # 5
    a0 = 1;
    a1 = 2;
    a2 = 3;
    a3 = 4;
    a4 = 5;
    a5 = 6;
    
    # 5
    
    s = 6'b000001;
    
    # 5

    s = 6'b000010;
    
    # 5
    s = 6'b000100;
    
    #5
    s = 6'b001000;
    
    #5
    s = 6'b010000;
    
    #5
    s = 6'b100000;
    #5
    
    $finish;
    
end


   // Enc42 test
   initial begin
      $monitor("At time %t, a= %d, b = %d", $time, a, b);
      $dumpfile("combinational_tb.vcd");
      $dumpvars(0, combinational_tb);

      # 5
	a = 0;

      # 5
	a = 1;
      # 5
	a = 2;
      # 5
	a = 3;
      # 5
	a = 4;
      # 5
	a = 5;
      # 5
	a = 6;
      # 5
	a = 7;
      # 5
	a = 8;
      # 5
	a = 9;
      # 5
	a = 10;
      # 5
	a = 11;
      # 5
	a = 12;
      # 5
	a = 13;
      # 5
	a = 14;
      # 5
	a = 15;
      # 5
	$finish;	
   end 


   // Enc42a test
   initial begin
      $monitor("At time %t, a= %d, b = %d, c = %d", $time, a, b, c);
      $dumpfile("combinational_tb.vcd");
      $dumpvars(0, combinational_tb);

      # 5
	a = 0;
      # 5
	a = 1;
      # 5
	a = 2;
      # 5
	a = 3;
      # 5
	a = 4;
      # 5
	a = 5;
      # 5
	a = 6;
      # 5
	a = 7;
      # 5
	a = 8;
      # 5
	a = 9;
      # 5
	a = 10;
      # 5
	a = 11;
      # 5
	a = 12;
      # 5
	a = 13;
      # 5
	a = 14;
      # 5
	a = 15;
      # 5
	$finish;	
   end 

   // Enc164 test
   initial begin
      $monitor("At time %t, a= %d, b = %d", $time, a, b);
      $dumpfile("combinational_tb.vcd");
      $dumpvars(0, combinational_tb);

      # 5
	a = 0;
      repeat (50) # 5 a = a + 1;
       
      $finish;
   end
  
   // Arb test
   initial begin
      $monitor("At time %t, r= %d, g= %d", $time, r, g);
      $dumpfile("combinational_tb.vcd");
      $dumpvars(0, combinational_tb);

      # 5
	r = 0;
      repeat (50) # 5 r = r + 1;
       
      $finish;
   end 

   // RArb test
   initial begin
      $monitor("At time %t, r= %d, g= %d", $time, r, g);
      $dumpfile("combinational_tb.vcd");
      $dumpvars(0, combinational_tb);

      # 5
	r = 0;
      repeat (50) # 5 r = r + 1;
       
      $finish;
   end

    // Priority Encoder test
   initial begin
      $monitor("At time %t, r= %d, b= %d", $time, r, b);
      $dumpfile("combinational_tb.vcd");
      $dumpvars(0, combinational_tb);

      # 5
	r = 0;
      repeat (50) # 5 r = r + 1;
       
      $finish;
   end

   initial begin
      $monitor("At time %t, a= %d, b= %d, eq= %d", $time, a, b, eq);
      $dumpfile("combinational_tb.vcd");
      $dumpvars(0, combinational_tb);

      # 5
      a = 0;
      b = 0;
      # 5
      a = 1;
      b = 1;
      # 5
      a = 27;
      b = 27;
      # 5
      a = 1;
      b = 2;
      
      
        
      
      repeat (50) begin
	 # 5
	 a = a + 1;
	 b = b + 1;
	 
      end
      
       
      $finish;
   end
*/
initial begin
      $monitor("At time %t, a= %d, b= %d, gt= %d", $time, a, b, gt);
      $dumpfile("combinational_tb.vcd");
      $dumpvars(0, combinational_tb);

      # 5
      a = 0;
      b = 0;
      # 5
      a = 1;
      b = 1;
      # 5
      a = 27;
      b = 27;
      # 5
      a = 1;
      b = 2;
      
      
        
      
      repeat (50) begin
	 # 5
	 a = a + 1;
	 b = b + 1;
      end
   
      # 5
      a = 2;
      b = 1;
      
	 
      repeat (50) begin
	 # 5
	 a = a + 1;
	 b = b + 1;
      end
      
       
      $finish;
   end   
   
endmodule

digital-building-blocks/combinational_tb.vcd
$date
	Sun Apr 30 18:51:43 2023
$end
$version
	Icarus Verilog
$end
$timescale
	1ps
$end
$scope module combinational_tb $end
$var wire 1 ! gt $end
$var reg 8 " a [7:0] $end
$var reg 8 # b [7:0] $end
$scope module mc $end
$var wire 8 $ a [7:0] $end
$var wire 8 % b [7:0] $end
$var wire 8 & eqi [7:0] $end
$var wire 8 ' gti [7:0] $end
$var wire 9 ( gtb [8:0] $end
$var wire 1 ! gt $end
$upscope $end
$upscope $end
$enddefinitions $end
#0
$dumpvars
bx0 (
bx '
bx &
bx %
bx $
bx #
bx "
x!
$end
#5000
0!
b0 (
b11111111 &
b0 '
b0 #
b0 %
b0 "
b0 $
#10000
0!
b0 (
b0 '
b1 #
b1 %
b1 "
b1 $
#15000
0!
b0 (
b0 '
b11011 #
b11011 %
b11011 "
b11011 $
#20000
b10 (
b1 '
b11111100 &
b10 #
b10 %
b1 "
b1 $
#25000
0!
b0 (
b11111110 &
b0 '
b11 #
b11 %
b10 "
b10 $
#30000
b110 (
b11 '
b11111000 &
b100 #
b100 %
b11 "
b11 $
#35000
0!
b0 (
b11111110 &
b0 '
b101 #
b101 %
b100 "
b100 $
#40000
b10 (
b1 '
b11111100 &
b110 #
b110 %
b101 "
b101 $
#45000
0!
b0 (
b11111110 &
b0 '
b111 #
b111 %
b110 "
b110 $
#50000
b1110 (
b111 '
b11110000 &
b1000 #
b1000 %
b111 "
b111 $
#55000
0!
b0 (
b11111110 &
b0 '
b1001 #
b1001 %
b1000 "
b1000 $
#60000
b10 (
b1 '
b11111100 &
b1010 #
b1010 %
b1001 "
b1001 $
#65000
0!
b0 (
b11111110 &
b0 '
b1011 #
b1011 %
b1010 "
b1010 $
#70000
b110 (
b11 '
b11111000 &
b1100 #
b1100 %
b1011 "
b1011 $
#75000
0!
b0 (
b11111110 &
b0 '
b1101 #
b1101 %
b1100 "
b1100 $
#80000
b10 (
b1 '
b11111100 &
b1110 #
b1110 %
b1101 "
b1101 $
#85000
0!
b0 (
b11111110 &
b0 '
b1111 #
b1111 %
b1110 "
b1110 $
#90000
b11110 (
b1111 '
b11100000 &
b10000 #
b10000 %
b1111 "
b1111 $
#95000
0!
b0 (
b11111110 &
b0 '
b10001 #
b10001 %
b10000 "
b10000 $
#100000
b10 (
b1 '
b11111100 &
b10010 #
b10010 %
b10001 "
b10001 $
#105000
0!
b0 (
b11111110 &
b0 '
b10011 #
b10011 %
b10010 "
b10010 $
#110000
b110 (
b11 '
b11111000 &
b10100 #
b10100 %
b10011 "
b10011 $
#115000
0!
b0 (
b11111110 &
b0 '
b10101 #
b10101 %
b10100 "
b10100 $
#120000
b10 (
b1 '
b11111100 &
b10110 #
b10110 %
b10101 "
b10101 $
#125000
0!
b0 (
b11111110 &
b0 '
b10111 #
b10111 %
b10110 "
b10110 $
#130000
b1110 (
b111 '
b11110000 &
b11000 #
b11000 %
b10111 "
b10111 $
#135000
0!
b0 (
b11111110 &
b0 '
b11001 #
b11001 %
b11000 "
b11000 $
#140000
b10 (
b1 '
b11111100 &
b11010 #
b11010 %
b11001 "
b11001 $
#145000
0!
b0 (
b11111110 &
b0 '
b11011 #
b11011 %
b11010 "
b11010 $
#150000
b110 (
b11 '
b11111000 &
b11100 #
b11100 %
b11011 "
b11011 $
#155000
0!
b0 (
b11111110 &
b0 '
b11101 #
b11101 %
b11100 "
b11100 $
#160000
b10 (
b1 '
b11111100 &
b11110 #
b11110 %
b11101 "
b11101 $
#165000
0!
b0 (
b11111110 &
b0 '
b11111 #
b11111 %
b11110 "
b11110 $
#170000
b111110 (
b11111 '
b11000000 &
b100000 #
b100000 %
b11111 "
b11111 $
#175000
0!
b0 (
b11111110 &
b0 '
b100001 #
b100001 %
b100000 "
b100000 $
#180000
b10 (
b1 '
b11111100 &
b100010 #
b100010 %
b100001 "
b100001 $
#185000
0!
b0 (
b11111110 &
b0 '
b100011 #
b100011 %
b100010 "
b100010 $
#190000
b110 (
b11 '
b11111000 &
b100100 #
b100100 %
b100011 "
b100011 $
#195000
0!
b0 (
b11111110 &
b0 '
b100101 #
b100101 %
b100100 "
b100100 $
#200000
b10 (
b1 '
b11111100 &
b100110 #
b100110 %
b100101 "
b100101 $
#205000
0!
b0 (
b11111110 &
b0 '
b100111 #
b100111 %
b100110 "
b100110 $
#210000
b1110 (
b111 '
b11110000 &
b101000 #
b101000 %
b100111 "
b100111 $
#215000
0!
b0 (
b11111110 &
b0 '
b101001 #
b101001 %
b101000 "
b101000 $
#220000
b10 (
b1 '
b11111100 &
b101010 #
b101010 %
b101001 "
b101001 $
#225000
0!
b0 (
b11111110 &
b0 '
b101011 #
b101011 %
b101010 "
b101010 $
#230000
b110 (
b11 '
b11111000 &
b101100 #
b101100 %
b101011 "
b101011 $
#235000
0!
b0 (
b11111110 &
b0 '
b101101 #
b101101 %
b101100 "
b101100 $
#240000
b10 (
b1 '
b11111100 &
b101110 #
b101110 %
b101101 "
b101101 $
#245000
0!
b0 (
b11111110 &
b0 '
b101111 #
b101111 %
b101110 "
b101110 $
#250000
b11110 (
b1111 '
b11100000 &
b110000 #
b110000 %
b101111 "
b101111 $
#255000
0!
b0 (
b11111110 &
b0 '
b110001 #
b110001 %
b110000 "
b110000 $
#260000
b10 (
b1 '
b11111100 &
b110010 #
b110010 %
b110001 "
b110001 $
#265000
0!
b0 (
b11111110 &
b0 '
b110011 #
b110011 %
b110010 "
b110010 $
#270000
b110 (
b11 '
b11111000 &
b110100 #
b110100 %
b110011 "
b110011 $
#275000
1!
b111111100 (
b11111100 &
b10 '
b1 #
b1 %
b10 "
b10 $
#280000
1!
b111111110 (
b1 '
b11111110 &
b10 #
b10 %
b11 "
b11 $
#285000
b111111000 (
b11111000 &
b100 '
b11 #
b11 %
b100 "
b100 $
#290000
1!
b111111110 (
b1 '
b11111110 &
b100 #
b100 %
b101 "
b101 $
#295000
b111111100 (
b11111100 &
b10 '
b101 #
b101 %
b110 "
b110 $
#300000
1!
b111111110 (
b1 '
b11111110 &
b110 #
b110 %
b111 "
b111 $
#305000
b111110000 (
b11110000 &
b1000 '
b111 #
b111 %
b1000 "
b1000 $
#310000
1!
b111111110 (
b1 '
b11111110 &
b1000 #
b1000 %
b1001 "
b1001 $
#315000
b111111100 (
b11111100 &
b10 '
b1001 #
b1001 %
b1010 "
b1010 $
#320000
1!
b111111110 (
b1 '
b11111110 &
b1010 #
b1010 %
b1011 "
b1011 $
#325000
b111111000 (
b11111000 &
b100 '
b1011 #
b1011 %
b1100 "
b1100 $
#330000
1!
b111111110 (
b1 '
b11111110 &
b1100 #
b1100 %
b1101 "
b1101 $
#335000
b111111100 (
b11111100 &
b10 '
b1101 #
b1101 %
b1110 "
b1110 $
#340000
1!
b111111110 (
b1 '
b11111110 &
b1110 #
b1110 %
b1111 "
b1111 $
#345000
b111100000 (
b11100000 &
b10000 '
b1111 #
b1111 %
b10000 "
b10000 $
#350000
1!
b111111110 (
b1 '
b11111110 &
b10000 #
b10000 %
b10001 "
b10001 $
#355000
b111111100 (
b11111100 &
b10 '
b10001 #
b10001 %
b10010 "
b10010 $
#360000
1!
b111111110 (
b1 '
b11111110 &
b10010 #
b10010 %
b10011 "
b10011 $
#365000
b111111000 (
b11111000 &
b100 '
b10011 #
b10011 %
b10100 "
b10100 $
#370000
1!
b111111110 (
b1 '
b11111110 &
b10100 #
b10100 %
b10101 "
b10101 $
#375000
b111111100 (
b11111100 &
b10 '
b10101 #
b10101 %
b10110 "
b10110 $
#380000
1!
b111111110 (
b1 '
b11111110 &
b10110 #
b10110 %
b10111 "
b10111 $
#385000
b111110000 (
b11110000 &
b1000 '
b10111 #
b10111 %
b11000 "
b11000 $
#390000
1!
b111111110 (
b1 '
b11111110 &
b11000 #
b11000 %
b11001 "
b11001 $
#395000
b111111100 (
b11111100 &
b10 '
b11001 #
b11001 %
b11010 "
b11010 $
#400000
1!
b111111110 (
b1 '
b11111110 &
b11010 #
b11010 %
b11011 "
b11011 $
#405000
b111111000 (
b11111000 &
b100 '
b11011 #
b11011 %
b11100 "
b11100 $
#410000
1!
b111111110 (
b1 '
b11111110 &
b11100 #
b11100 %
b11101 "
b11101 $
#415000
b111111100 (
b11111100 &
b10 '
b11101 #
b11101 %
b11110 "
b11110 $
#420000
1!
b111111110 (
b1 '
b11111110 &
b11110 #
b11110 %
b11111 "
b11111 $
#425000
b111000000 (
b11000000 &
b100000 '
b11111 #
b11111 %
b100000 "
b100000 $
#430000
1!
b111111110 (
b1 '
b11111110 &
b100000 #
b100000 %
b100001 "
b100001 $
#435000
b111111100 (
b11111100 &
b10 '
b100001 #
b100001 %
b100010 "
b100010 $
#440000
1!
b111111110 (
b1 '
b11111110 &
b100010 #
b100010 %
b100011 "
b100011 $
#445000
b111111000 (
b11111000 &
b100 '
b100011 #
b100011 %
b100100 "
b100100 $
#450000
1!
b111111110 (
b1 '
b11111110 &
b100100 #
b100100 %
b100101 "
b100101 $
#455000
b111111100 (
b11111100 &
b10 '
b100101 #
b100101 %
b100110 "
b100110 $
#460000
1!
b111111110 (
b1 '
b11111110 &
b100110 #
b100110 %
b100111 "
b100111 $
#465000
b111110000 (
b11110000 &
b1000 '
b100111 #
b100111 %
b101000 "
b101000 $
#470000
1!
b111111110 (
b1 '
b11111110 &
b101000 #
b101000 %
b101001 "
b101001 $
#475000
b111111100 (
b11111100 &
b10 '
b101001 #
b101001 %
b101010 "
b101010 $
#480000
1!
b111111110 (
b1 '
b11111110 &
b101010 #
b101010 %
b101011 "
b101011 $
#485000
b111111000 (
b11111000 &
b100 '
b101011 #
b101011 %
b101100 "
b101100 $
#490000
1!
b111111110 (
b1 '
b11111110 &
b101100 #
b101100 %
b101101 "
b101101 $
#495000
b111111100 (
b11111100 &
b10 '
b101101 #
b101101 %
b101110 "
b101110 $
#500000
1!
b111111110 (
b1 '
b11111110 &
b101110 #
b101110 %
b101111 "
b101111 $
#505000
b111100000 (
b11100000 &
b10000 '
b101111 #
b101111 %
b110000 "
b110000 $
#510000
1!
b111111110 (
b1 '
b11111110 &
b110000 #
b110000 %
b110001 "
b110001 $
#515000
b111111100 (
b11111100 &
b10 '
b110001 #
b110001 %
b110010 "
b110010 $
#520000
1!
b111111110 (
b1 '
b11111110 &
b110010 #
b110010 %
b110011 "
b110011 $
#525000
b111111000 (
b11111000 &
b100 '
b110011 #
b110011 %
b110100 "
b110100 $
