rv32-single/rv32-single.srcs/sources_1/new/data_memory.v
`timescale 1ns / 1ps

module data_memory (
	input r,
	input [31:0] address,
	input write_en,
	input read_en,
	input [31:0] write_data,
	output reg [31:0] read_data
);
	
	parameter MEMSIZE = 1024; 
	reg [31:0] memory[0:MEMSIZE-1];
    
    integer i;
	initial begin
	   for (i = 0; i < MEMSIZE - 1; i = i + 1) begin
            if (i == 4) begin
                memory[i] = 68;
            end 
            else begin
                memory[i] = 0;
            end	   
	   end
	end
	
	always @(*) begin
		if (r) begin
		  read_data = 0;
		end
		else if (write_en) begin
			memory[address] = write_data;
		end
		else if (read_en) begin
			read_data = memory[address];
		end
	end


endmodule

rv32-pipelined/rv32-pipelined.srcs/sources_1/new/defines.v
// OPCODE by type
`define op_r 7'b0110011
`define op_b 7'b1100011
`define op_s 7'b0100011
`define op_l 7'b0000011
`define op_i 7'b0010011

// RV32I opcodes
`define op_lui 7'b0110111
`define op_auipe 7'b0010111
`define op_jal 7'b1101111
`define op_jalr 7'b1100111
`define op_beq 7'b1100011
`define op_bne 7'b1100011
`define op_blt 7'b1100011
`define op_bge 7'b1100011
`define op_bltu 7'b1100011
`define op_bgeu 7'b1100011
`define op_lb 7'b0000011
`define op_lh 7'b0000011
`define op_lw 7'b0000011
`define op_lbu 7'b0000011
`define op_lhu 7'b0000011
`define op_sb 7'b0100011
`define op_sh 7'b0100011
`define op_sw 7'b0100011
`define op_addi 7'b0010011
`define op_slti 7'b0010011
`define op_sltiu 7'b0010011
`define op_xori 7'b0010011
`define op_ori 7'b0010011
`define op_andi 7'b0010011
`define op_slli 7'b0010011
`define op_srli 7'b0010011
`define op_srai 7'b0010011
`define op_add 7'b0110011
`define op_sub 7'b0110011
`define op_sll 7'b0110011
`define op_slt 7'b0110011
`define op_sltu 7'b0110011
`define op_xor 7'b0110011
`define op_srl 7'b0110011
`define op_sra 7'b0110011
`define op_or 7'b0110011
`define op_and 7'b0110011
`define op_fence 7'b0001111
`define op_fencei 7'b0001111
`define op_ecall 7'b1110011
`define op_ebreak 7'b1110011
`define op_csrrw 7'b1110011
`define op_csrrs 7'b1110011
`define op_csrrc 7'b1110011
`define op_csrrwi 7'b1110011
`define op_csrrsi 7'b1110011
`define op_csrrci 7'b1110011

// RV32I funct3 codes
`define f3_jalr 3'b000
`define f3_beq 3'b000
`define f3_bne 3'b001
`define f3_blt 3'b100
`define f3_bge 3'b101
`define f3_bltu 3'b110
`define f3_bgeu 3'b111
`define f3_lb 3'b000
`define f3_lh 3'b001
`define f3_lw 3'b010
`define f3_lbu 3'b100
`define f3_lhu 3'b101
`define f3_sb 3'b000
`define f3_sh 3'b001
`define f3_sw 3'b010
`define f3_addi 3'b000
`define f3_slti 3'b010
`define f3_sltiu 3'b011
`define f3_xori 3'b100
`define f3_ori 3'b110
`define f3_andi 3'b111
`define f3_slli 3'b001
`define f3_srli 3'b101
`define f3_srai 3'b101
`define f3_add 3'b000
`define f3_sub 3'b000
`define f3_sll 3'b001
`define f3_slt 3'b010
`define f3_sltu 3'b011
`define f3_xor 3'b100
`define f3_srl 3'b101
`define f3_sra 3'b101
`define f3_or 3'b110
`define f3_and 3'b111
`define f3_fence 3'b000
`define f3_fencei 3'b001
`define f3_ecall 3'b000
`define f3_ebreak 3'b000
`define f3_csrrw 3'b001
`define f3_csrrs 3'b010
`define f3_csrrc 3'b011
`define f3_csrrwi 3'b101
`define f3_csrrsi 3'b110
`define f3_csrrci 3'b111

// RV32I func7 codes
`define  f7_slli 7'b0000000
`define f7_srli 7'b0000000
`define f7_srai 7'b0100000
`define f7_add 7'b0000000
`define f7_sub 7'b0100000
`define f7_sll 7'b0000000
`define f7_slt 7'b0000000
`define f7_sltu 7'b0000000
`define f7_xor 7'b0000000
`define f7_srl 7'b0000000
`define f7_sra 7'b0100000
`define f7_or 7'b0000000
`define f7_and 7'b0000000

// RV32M opcodes
`define op_mul 7'b0110011
`define op_mulh 7'b0110011
`define op_mulhsu 7'b0110011
`define op_mulhu 7'b0110011
`define op_div 7'b0110011
`define op_divu 7'b0110011
`define op_rem 7'b0110011
`define op_remu 7'b0110011

// RV32M f7 codes
`define f7_mul 7'b0000001
`define f7_mulh 7'b0000001
`define f7_mulhsu 7'b0000001
`define f7_mulhu 7'b0000001
`define f7_div 7'b0000001
`define f7_divu 7'b0000001
`define f7_rem 7'b0000001
`define f7_remu 7'b0000001

// RV32M f3 codes
`define f3_mul 3'b000
`define f3_mulh 3'b001
`define f3_mulhsu 3'b010
`define f3_mulhu 3'b011
`define f3_div 3'b100
`define f3_divu 3'b101
`define f3_rem 3'b110
`define f3_remu 3'b111

// ALU Opcodes
// Control for alu opcode
`define ALU_ADD 4'b0001
`define ALU_ADDH 4'b0010
`define ALU_ADDB 4'b0011
`define ALU_ADDU 4'b0100
`define ALU_SUB 4'b0101
`define ALU_SLL 4'b0110
`define ALU_SLT 4'b0111
`define ALU_SLTU 4'b1000
`define ALU_XOR 4'b1001
`define ALU_SRL 4'b1010
`define ALU_SRA 4'b1011
`define ALU_OR 4'b1100
`define ALU_AND 4'b1101

simple-cpus/rv32-single/rv32-single.srcs/sources_1/new/alu.v
`include "defines.v"
`timescale 1ns / 1ps

// Page 351 of pdf (270 in actual textbook)

module alu (
	input r,
	input [3:0] alu_op,
	input [31:0] alu_in1,
	input [31:0] alu_in2,
	output wire zero,
	output reg [31:0] alu_result
);
	
	localparam ADD = 4'b0010;
	localparam SUB = 4'b0110;
	localparam AND = 4'b0000;
	localparam OR = 4'b0001;
	
	wire signed [31:0] alu_in1_signed = alu_in1;
	wire signed [31:0] alu_in2_signed = alu_in2;
	
	assign zero = (alu_in1_signed - alu_in2_signed == 0) ? 1'b1 : 1'b0;
	
	always @(*) begin
		if (r) begin
            alu_result = 0;	
		end
		else begin
		  case(alu_op)
			ADD : alu_result = alu_in1_signed + alu_in2_signed; // add
			SUB : alu_result = alu_in1_signed - alu_in2_signed; // sub					
			OR : alu_result = alu_in1_signed | alu_in2_signed; // or
			AND : alu_result = alu_in1_signed & alu_in2_signed; // and 			
			default : alu_result = 0;
		  endcase
		end
	end
	
endmodule

rv32I-cpu/rv32I-cpu.srcs/sources_1/imports/new/alu_control.v
`timescale 1ns / 1ps

// Page 352 of pdf (271 in actual textbook)

module alu_control(
    input wire r,
    input wire [1:0] alu_op,
    input wire [9:0] func_code, //{f7, f3}
    output reg [3:0] operation
);

    always @(*) begin
        if (r) begin
            operation = 4'b0000;
        end
        else begin
            casex({alu_op, func_code})
                {2'b00, 10'bxxxxxxxxxx} : operation = 4'b0010;
                {2'bx1, 10'bxxxxxxxxxx} : operation = 4'b0110;
                {2'b1x, 10'b0000000000} : operation = 4'b0010;
                {2'b1x, 10'b0100000000} : operation = 4'b0110;
                {2'b1x, 10'b0000000111} : operation = 4'b0000;
                {2'b1x, 10'b0000000110} : operation = 4'b0001;
                default : operation = 4'b0000;
            endcase
        end
    end


endmodule

simple-cpus/rv32-single/rv32-single.srcs/sources_1/new/immediate_generator.v
`timescale 1ns / 1ps
`include "defines.v"

module immediate_generator(
    input r,
    input [31:0] instruction,
    output reg [31:0] imm_sext
);

    always @(*) begin
        if (r) begin
            imm_sext = 0;
        end
        else begin
            case(instruction[6:0])
            `op_b : begin
                imm_sext = {{19{instruction[31]}}, instruction[31], instruction[7], instruction[30:25], instruction[11:8], 1'b0};
            end
            `op_i : begin
                imm_sext = {{20{instruction[31]}}, instruction[31:20]};
            end
            `op_s : begin
                imm_sext = {{20{instruction[31]}} ,instruction[31:25], instruction[11:7]};
            end
            `op_l : begin
                imm_sext = {{20{instruction[31]}}, instruction[31:20]};
            end
            `op_jal : begin
                imm_sext = {{12{instruction[31]}}, instruction[31], instruction[19:12], instruction[20], instruction[30:21]};
            end
            `op_jalr : begin
                imm_sext = {{20{instruction[31]}}, instruction[31:20]};
            end
            `op_lui : begin
                imm_sext = {{12{instruction[31]}}, instruction[31:12]};
            end
            `op_auipe : begin
                imm_sext = {{12{instruction[31]}}, instruction[31:12]};
            end
            default : begin
                imm_sext = 0;
            end
            endcase
        end
    end
    
endmodule

rv32-single/rv32-single.srcs/sources_1/new/register_file.v
`timescale 1ns / 1ps
module register_file (
    input wire r,
    input wire [4:0] rs1, 
    input wire [4:0] rs2, 
    input wire [4:0] write_addr,
    input wire write_enable,
    input wire [31:0] write_data,
    output reg [31:0] read_data1,
    output reg [31:0] read_data2
);

    localparam REGSIZE = 32;
    localparam NUMREGS = 32;
    reg [REGSIZE-1:0] regs[0:NUMREGS - 1];
    
    integer i;
    initial begin
       for (i = 0; i < NUMREGS; i = i + 1) begin
           if (i == 1) begin
               regs[i] = 1;
           end
           
           else if (i == 2) begin
               regs[i] = 5;
           end
           
           else begin
               regs[i] = 0;
           end
       end
    end
    
    always @(*) begin
        if (r) begin
            read_data1 = 0;
            read_data2 = 0;
        end
        else begin
            if (write_enable) begin
                regs[write_addr] = write_data;
                read_data1 = (rs1 == 0) ? 32'd0 : regs[rs1];
                read_data2 = (rs2 == 0) ? 32'd0 : regs[rs2];
            end
            else begin
                read_data1 = (rs1 == 0) ? 32'd0 : regs[rs1];
                read_data2 = (rs2 == 0) ? 32'd0 : regs[rs2];
            end
        end
    end
  
endmodule

rv32-single/rv32-single.srcs/sources_1/new/control_unit.v
`timescale 1ns / 1ps
`include "defines.v"

// Truth table on page 362 (281 in actual book) of pdf of HP1 

module control_unit(
    input wire r,
    input wire [6:0] op_code,
    output wire mem_read,
    output wire mem_2_reg,
    output wire mem_write,
    output wire alu_src,
    output wire [1:0] alu_op,
    output wire reg_write,
    output wire branch
);

    assign mem_read = (op_code == `op_l && !r) ? 1'b1 : 1'b0;
    
    assign mem_2_reg = (op_code == `op_l && !r) ? 1'b1 : 1'b0;	
    
    assign mem_write = (op_code == `op_s && !r) ? 1'b1 : 1'b0;	
    
    assign alu_src = ((op_code == `op_s || op_code == `op_l) && !r) ? 1'b1 : 1'b0;	
    
    assign alu_op = (op_code == `op_r && !r) ? 2'b10 : 
                    (op_code == `op_b && !r) ? 2'b01 : 2'b00;	
    
    assign reg_write = ((op_code == `op_r || op_code == `op_l) && !r) ? 1'b1 : 1'b0;	
	     
    assign branch = (op_code == `op_b && !r) ? 1'b1 : 1'b0;
    	               
endmodule

rv32-single/rv32-single.srcs/sources_1/new/instruction_memory.v
`timescale 1ns / 1ps
module instruction_memory (
	input r,
	input [31:0] read_addr,
	output reg [31:0] instr,
	input [31:0] i_mem_addr,
	input [31:0] i_mem_data,
	input i_mem_write
);

    localparam MEMSIZE = 1024;
    localparam MEMWIDTH = 32;
    reg [MEMWIDTH-1:0] i_memory[0:MEMSIZE-1];
	
	always @(*) begin
		if (r) begin
			instr = 32'b0;
		end
		else if (i_mem_write) begin
		    i_memory[i_mem_addr] = i_mem_data;
		end
		else begin
			instr = i_memory[read_addr];
		end
	end
	
    // Complete test
    // Assumes x1 = 1, x2 = 5, and rest of registers are 0 at runtime    
    integer i;
	initial begin
	   for (i = 0; i < MEMSIZE - 1; i = i + 1) begin
            
            if (i == 0) begin
                i_memory[i] = 32'b0000000_00010_00001_000_00011_0110011; // add x3, x1, x2        
            end
            
            else if (i == 1) begin
                i_memory[i] = 32'b0100000_00001_00010_000_00100_0110011; // sub x4, x1, x2
            end
            
            else if (i == 2) begin
                i_memory[i] = 32'b0000000_00010_00001_111_00101_0110011; // and x5, x1, x3
            end
            
            else if(i == 3) begin
                i_memory[i] = 32'b0000000_00010_00100_110_00110_0110011; // or x6, x4, x2           
            end
            
            else if (i == 4) begin
                i_memory[i] = 32'b000000000000_00100_010_00111_0000011; // lw x7, offset(4)          
            end
            
            else if (i == 5) begin
                i_memory[i] = 32'b0000000_00111_00000_010_00000_0100011; // sw x7, offset(0)
            end
            
            else if (i == 6) begin
                i_memory[i] = 32'b0000000_00110_00010_000_01010_1100011; // beq x2, x6, offset
            end
            
            else begin
                i_memory[i] = 0;
            end	   
	    end
	end
    
	
endmodule

rv32-single/rv32-single.srcs/sources_1/new/riscv_cpu.v
`timescale 1ns / 1ps

module riscv_cpu(
    input clk,
    input r,
    input [31:0] i_mem_addr,
	input [31:0] i_mem_data,
	input i_mem_write
);

wire [31:0] instr, imm_sext;
reg [31:0] PC;
wire branch, zero;
always @(posedge clk) begin
    if (r) begin
        PC <= 0;
    end
    else begin
        PC <= (branch && zero) ? PC + imm_sext : PC + 1;
    end
end

instruction_memory im1(
	.r(r),
	.read_addr(PC),
	.instr(instr),
	.i_mem_addr(i_mem_addr),
	.i_mem_data(i_mem_data),
	.i_mem_write(i_mem_write)
);

wire mem_read, mem_2_reg, mem_write, alu_src, reg_write;
wire [1:0] alu_op;
control_unit cu1(
    .r(r),
    .op_code(instr[6:0]),
    .mem_read(mem_read),
    .mem_2_reg(mem_2_reg),
    .mem_write(mem_write),
    .alu_src(alu_src),
    .alu_op(alu_op),
    .reg_write(reg_write),
    .branch(branch)
);

wire [31:0] read_data1, read_data2, write_data;
register_file rf1(
    .r(r),
    .rs1(instr[19:15]), 
    .rs2(instr[24:20]), 
    .write_addr(instr[11:7]),
    .write_enable(reg_write),
    .write_data(write_data),
    .read_data1(read_data1),
    .read_data2(read_data2)
);

immediate_generator ig1(
    .r(r),
    .instruction(instr),
    .imm_sext(imm_sext)
);

wire [3:0] operation;
alu_control ac1(
    .r(r),
    .alu_op(alu_op),
    .func_code({instr[31:25], instr[14:12]}), //{f7, f3}
    .operation(operation)
);

wire [31:0] alu_in1, alu_in2, alu_result;
assign alu_in1 = read_data1;
assign alu_in2 = (alu_src) ? imm_sext : read_data2;
alu alu1(
    .r(r),
	.alu_op(operation),
	.alu_in1(alu_in1),
	.alu_in2(alu_in2),
	.zero(zero),
	.alu_result(alu_result)
);

wire [31:0] read_data;
data_memory dm1(
	.r(r),
	.address(alu_result),
	.write_en(mem_write),
	.read_en(mem_read),
	.write_data(read_data2),
	.read_data(read_data)
);
    
assign write_data = (mem_2_reg) ? read_data : alu_result;
   
endmodule

rv32-single/rv32-single.srcs/sources_1/new/riscv_cpu_tb.v
`timescale 1ns / 1ps
module riscv_cpu_tb();

    reg clk = 1;
    reg r;
    reg [31:0] i_mem_addr;
	reg [31:0] i_mem_data;
	reg i_mem_write;
    
    riscv_cpu dut(
        .clk(clk),
        .r(r),
        .i_mem_addr(i_mem_addr),
        .i_mem_data(i_mem_data),
        .i_mem_write(i_mem_write)
    );
    
    always begin
        # 5 clk = ~clk;    
    end
    
    initial begin
        $monitor("At time %t", $time);
      	$dumpfile("riscv_cpu_tb.vcd");
      	$dumpvars(0, riscv_cpu_tb);
      	r = 1;
      	i_mem_addr = 0;
      	i_mem_data = 0;
      	i_mem_write = 0;
      	# 5
      	r = 0;
      	# 20
      	$finish;
    end
    
endmodule

rv32-single/rv32-single.sim/sim_1/behav/xsim/riscv_cpu_tb.vcd
$date
   Mon Dec  4 13:03:55 2023
$end
$version
  2023.1
$end
$timescale
  1ps
$end
$scope module riscv_cpu_tb $end
$var reg 1 ! clk $end
$var reg 1 " r $end
$var reg 32 # i_mem_addr [31:0] $end
$var reg 32 $ i_mem_data [31:0] $end
$var reg 1 % i_mem_write $end
$scope module dut $end
$var wire 1 & clk $end
$var wire 1 ' r $end
$var wire 32 ( i_mem_addr [31:0] $end
$var wire 32 ) i_mem_data [31:0] $end
$var wire 1 * i_mem_write $end
$var wire 32 + instr [31:0] $end
$var wire 32 , imm_sext [31:0] $end
$var reg 32 - PC [31:0] $end
$var wire 1 . branch $end
$var wire 1 / zero $end
$var wire 1 0 mem_read $end
$var wire 1 1 mem_2_reg $end
$var wire 1 2 mem_write $end
$var wire 1 3 alu_src $end
$var wire 1 4 reg_write $end
$var wire 2 5 alu_op [1:0] $end
$var wire 32 6 read_data1 [31:0] $end
$var wire 32 7 read_data2 [31:0] $end
$var wire 32 8 write_data [31:0] $end
$var wire 4 9 operation [3:0] $end
$var wire 32 : alu_in1 [31:0] $end
$var wire 32 ; alu_in2 [31:0] $end
$var wire 32 < alu_result [31:0] $end
$var wire 32 = read_data [31:0] $end
$scope module im1 $end
$var wire 1 ' r $end
$var wire 32 > read_addr [31:0] $end
$var reg 32 ? instr [31:0] $end
$var wire 32 ( i_mem_addr [31:0] $end
$var wire 32 ) i_mem_data [31:0] $end
$var wire 1 * i_mem_write $end
$var integer 32 @ i [31:0] $end
$upscope $end
$scope module cu1 $end
$var wire 1 ' r $end
$var wire 7 A op_code [6:0] $end
$var wire 1 0 mem_read $end
$var wire 1 1 mem_2_reg $end
$var wire 1 2 mem_write $end
$var wire 1 3 alu_src $end
$var wire 2 5 alu_op [1:0] $end
$var wire 1 4 reg_write $end
$var wire 1 . branch $end
$upscope $end
$scope module rf1 $end
$var wire 1 ' r $end
$var wire 5 B rs1 [19:15] $end
$var wire 5 C rs2 [24:20] $end
$var wire 5 D write_addr [11:7] $end
$var wire 1 4 write_enable $end
$var wire 32 8 write_data [31:0] $end
$var reg 32 E read_data1 [31:0] $end
$var reg 32 F read_data2 [31:0] $end
$var integer 32 G i [31:0] $end
$upscope $end
$scope module ig1 $end
$var wire 1 ' r $end
$var wire 32 + instruction [31:0] $end
$var reg 32 H imm_sext [31:0] $end
$upscope $end
$scope module ac1 $end
$var wire 1 ' r $end
$var wire 2 5 alu_op [1:0] $end
$var wire 10 I func_code [9:0] $end
$var reg 4 J operation [3:0] $end
$upscope $end
$scope module alu1 $end
$var wire 1 ' r $end
$var wire 4 9 alu_op [3:0] $end
$var wire 32 : alu_in1 [31:0] $end
$var wire 32 ; alu_in2 [31:0] $end
$var wire 1 / zero $end
$var reg 32 K alu_result [31:0] $end
$var wire 32 L alu_in1_signed [31:0] $end
$var wire 32 M alu_in2_signed [31:0] $end
$upscope $end
$scope module dm1 $end
$var wire 1 ' r $end
$var wire 32 < address [31:0] $end
$var wire 1 2 write_en $end
$var wire 1 0 read_en $end
$var wire 32 7 write_data [31:0] $end
$var reg 32 N read_data [31:0] $end
$var integer 32 O i [31:0] $end
$upscope $end
$upscope $end
$upscope $end
$enddefinitions $end
#0
$dumpvars
1!
1"
b0 #
b0 $
0%
1&
1'
b0 (
b0 )
0*
b0 +
b0 ,
b0 -
0.
1/
00
01
02
03
04
b0 5
b0 6
b0 7
b0 8
b0 9
b0 :
b0 ;
b0 <
b0 =
b0 >
b0 ?
b1111111111 @
b0 A
b0 B
b0 C
b0 D
b0 E
b0 F
b100000 G
b0 H
b0 I
b0 J
b0 K
b0 L
b0 M
b0 N
b1111111111 O
$end
#5000
0!
0"
0&
0'
b1000001000000110110011 +
0/
14
b10 5
b1 6
b101 7
b110 8
b10 9
b1 :
b101 ;
b110 <
b1000001000000110110011 ?
b110011 A
b1 B
b10 C
b11 D
b1 E
b101 F
b10 J
b110 K
b1 L
b101 M
#10000
1!
1&
b1000000000100010000001000110011 +
b1 -
b101 6
b1 7
b100 8
b110 9
b101 :
b1 ;
b100 <
b1 >
b1000000000100010000001000110011 ?
b110011 A
b10 B
b1 C
b100 D
b101 E
b1 F
b100000000 I
b110 J
b100 K
b101 L
b1 M
#15000
0!
0&
#20000
1!
1&
b1000001111001010110011 +
b10 -
b1 6
b101 7
b1 8
b0 9
b1 :
b101 ;
b1 <
b10 >
b1000001111001010110011 ?
b110011 A
b1 B
b10 C
b101 D
b1 E
b101 F
b111 I
b0 J
b1 K
b1 L
b101 M
#25000
0!
0&
#30000
1!
1&
b1000100110001100110011 +
b11 -
b100 6
b101 8
b1 9
b100 :
b101 <
b11 >
b1000100110001100110011 ?
b110011 A
b100 B
b10 C
b110 D
b100 E
b110 I
b1 J
b101 K
b100 L
#35000
0!
0&
#40000
1!
1&
b100010001110000011 +
b100 -
10
11
13
b0 5
b0 7
b1000100 8
b10 9
b0 ;
b100 <
b1000100 =
b100 >
b100010001110000011 ?
b11 A
b100 B
b0 C
b111 D
b0 F
b10 I
b10 J
b100 K
b0 M
b1000100 N
#45000
0!
0&
#50000
1!
1&
b11100000010000000100011 +
b101 -
1/
00
01
12
04
b0 6
b1000100 7
b0 8
b0 :
b0 <
b101 >
b11100000010000000100011 ?
b100011 A
b0 B
b111 C
b0 D
b0 E
b1000100 F
b0 K
b0 L
#55000
0!
0&
#60000
1!
1&
b11000010000010101100011 +
b1010 ,
b110 -
1.
1/
02
03
b1 5
b101 6
b101 7
b0 8
b110 9
b101 :
b101 ;
b0 <
b110 >
b11000010000010101100011 ?
b1100011 A
b10 B
b110 C
b1010 D
b101 E
b101 F
b1010 H
b0 I
b110 J
b0 K
b101 L
b101 M
#65000
0!
0&
#70000
1!
1&
b0 +
b0 ,
b10000 -
0.
b0 5
b0 6
b0 7
b10 9
b0 :
b0 ;
b10000 >
b0 ?
b0 A
b0 B
b0 C
b0 D
b0 E
b0 F
b0 H
b10 J
b0 L
b0 M
#75000
0!
0&
#80000
1!
1&
b10001 -
b10001 >
#85000
0!
0&
#90000
1!
1&
b10010 -
b10010 >
#95000
0!
0&
#100000
1!
1&
b10011 -
b10011 >
#105000
0!
0&
#110000
1!
1&
b10100 -
b10100 >
#115000
0!
0&
#120000
1!
1&
b10101 -
b10101 >
